dags/__init__.py
dags/base_tables.py
dags/clickstream_sf.py
dags/financial_dag.py
dags/mrr_salesforce.py
dags/paid_marketing_dag.py
dags/product_metrics.py
dags/quickbooks_dag.py
dags/salesforce_lead_source.py
dags/salesforce_user_contacts.py
dags/search_console.py
dags/usage_salesforce.py
dags/sql/__init__.py
dags/sql/user_contacts/__init__.py
dags/sql/user_contacts/sf_user_contacts_query.py
plugins/__init__.py
plugins/functions/__init__.py
plugins/functions/sql_format.py
sql/__init__.py
sql/user_contacts/__init__.py
sql/user_contacts/sf_user_contacts_query.py
workstreamdatatech-0.0.2.dist-info/LICENSE
workstreamdatatech-0.0.2.dist-info/METADATA
workstreamdatatech-0.0.2.dist-info/WHEEL
workstreamdatatech-0.0.2.dist-info/top_level.txt
workstreamdatatech-0.0.2.dist-info/RECORD
